clownorelm/__init__.py
clownorelm/clownorelm.py
clownorelm/resources/mellow_corn_label.jpeg
clownorelm-0.1.4.dist-info/LICENSE
clownorelm-0.1.4.dist-info/METADATA
clownorelm-0.1.4.dist-info/WHEEL
clownorelm-0.1.4.dist-info/RECORD
