Metadata-Version: 2.1
Name: clownorelm
Version: 0.1.4
Summary: Package to be used for an upcoming presentation
License: Apache-2.0
Author: Birdwainer
Requires-Python: >=3.10,<4.0
Classifier: License :: OSI Approved :: Apache Software License
Classifier: Programming Language :: Python :: 3
Classifier: Programming Language :: Python :: 3.10
Classifier: Programming Language :: Python :: 3.11
Requires-Dist: ascii-magic (>=2.3.0,<3.0.0)
